dynamic_prompting/__init__.py
dynamic_prompting/embedings/__init__.py
dynamic_prompting/embedings/config.py
dynamic_prompting/embedings/embeddings.py
dynamic_prompting/knowledge_base/__init__.py
dynamic_prompting/knowledge_base/ann.py
dynamic_prompting/knowledge_base/config.py
dynamic_prompting/knowledge_base/knowledge_base.py
dynamic_prompting/llms/__init__.py
dynamic_prompting/llms/config.py
dynamic_prompting/llms/llm.py
dynamic_prompting/llms/prompt.py
dynamic_prompting/utils/__init__.py
dynamic_prompting/utils/utils.py
dynamic_prompting-0.2.6.dist-info/METADATA
dynamic_prompting-0.2.6.dist-info/WHEEL
dynamic_prompting-0.2.6.dist-info/top_level.txt
dynamic_prompting-0.2.6.dist-info/RECORD
