Metadata-Version: 2.1
Name: dynamic-prompting
Version: 0.2.6
Summary: Dynamic Few-Shot Prompting is a Python package that dynamically selects N samples that are contextually close to the user's task or query from a knowledge base (similar to RAG) to include in the prompt.
Author: Elmira Ghorbani
License: UNKNOWN
Project-URL: Github, https://github.com/ElmiraGhorbani/dynamic_prompting
Platform: UNKNOWN
Requires-Dist: einops (==0.8.0)
Requires-Dist: sentence-transformers (==3.0.1)
Requires-Dist: torch (==2.2.1)
Requires-Dist: transformers (==4.41.1)
Requires-Dist: meta-llama3 (==0.0.1)
Requires-Dist: pandas (==2.2.2)
